{"status": "000", "contests": [{"id": 10004, "href": "https://atcoder.jp/contests/masters2025-qual", "event": "The 2nd Masters Championship-qual-", "duration": 216000, "start_time": 174088800000, "end_time": 174090960000}, {"id": 10004, "href": "https://atcoder.jp/contests/abc375", "event": "Panasonic Programming Contest 2024\uff08AtCoder Beginner Contest 375\uff09", "duration": 60000, "start_time": 172873440000, "end_time": 172874040000}, {"id": 10002, "href": "https://www.codechef.com/START155", "event": "Starters 155", "duration": 72000, "start_time": 172848420000, "end_time": 172849140000}, {"id": 10004, "href": "https://atcoder.jp/contests/abc374", "event": "KEYENCE Programming Contest 2024\uff08AtCoder Beginner Contest 374\uff09", "duration": 60000, "start_time": 172812960000, "end_time": 172813560000}, {"id": 10004, "href": "https://atcoder.jp/contests/ahc038", "event": "Toyota Programming Contest 2024#10\uff08AtCoder Heuristic Contest 038\uff09", "duration": 8640000, "start_time": 172803600000, "end_time": 172890000000}, {"id": 10002, "href": "https://www.codechef.com/START154", "event": "Starters 154", "duration": 72000, "start_time": 172787940000, "end_time": 172788660000}, {"id": 10001, "href": "https://codeforces.com/contests/2011", "event": "Kotlin Heroes: Episode 11", "duration": 90000, "start_time": 172770690000, "end_time": 172771590000}, {"id": 10004, "href": "https://atcoder.jp/contests/agc068", "event": "AtCoder Grand Contest 068", "duration": 108000, "start_time": 172761120000, "end_time": 172762200000}, {"id": 10004, "href": "https://atcoder.jp/contests/abc373", "event": "AtCoder Beginner Contest 373", "duration": 60000, "start_time": 172752480000, "end_time": 172753080000}, {"id": 10002, "href": "https://www.codechef.com/START153", "event": "Starters 153", "duration": 72000, "start_time": 172727460000, "end_time": 172728180000}, {"id": 10001, "href": "https://codeforces.com/contests/2012", "event": "Kotlin Heroes: Practice 11", "duration": 6048000, "start_time": 172709850000, "end_time": 172770330000}, {"id": 10004, "href": "https://atcoder.jp/contests/arc184", "event": "AtCoder Regular Contest 184", "duration": 72000, "start_time": 172700640000, "end_time": 172701360000}, {"id": 10001, "href": "https://codeforces.com/contests/2014", "event": "Codeforces Round (Div. 3)", "duration": 81000, "start_time": 172692930000, "end_time": 172693740000}, {"id": 10004, "href": "https://atcoder.jp/contests/abc372", "event": "UNIQUE VISION Programming Contest 2024 Autumn (AtCoder Beginner Contest 372)", "duration": 60000, "start_time": 172692000000, "end_time": 172692600000}, {"id": 10001, "href": "https://codeforces.com/contests/2013", "event": "Codeforces Round (Div. 2)", "duration": 72000, "start_time": 172684290000, "end_time": 172685010000}, {"id": 10002, "href": "https://www.codechef.com/START152", "event": "Starters 152", "duration": 72000, "start_time": 172666980000, "end_time": 172667700000}, {"id": 10004, "href": "https://atcoder.jp/contests/ahc037", "event": "11th Asprova Programming Contest\uff08AtCoder Heuristic Contest 037\uff09", "duration": 144000, "start_time": 172639440000, "end_time": 172640880000}]}