{"status": "000", "contests": [{"id": 10001, "href": "http://codeforces.com/contests/1731", "event": "Codeforces Round (Div. 2)", "duration": 72000, "start_time": 167215170000, "end_time": 167215890000}, {"id": 10003, "href": "https://topcoder.com/community/events/", "event": "Marathon Match 142", "duration": 6048000, "start_time": 167043600000, "end_time": 167104080000}, {"id": 10003, "href": "https://topcoder.com/community/events/", "event": "SRM 842", "duration": 72000, "start_time": 166999680000, "end_time": 167000400000}, {"id": 10002, "href": "https://www.codechef.com/START67", "event": "Starters 67", "duration": 108000, "start_time": 166981860000, "end_time": 166982940000}, {"id": 10004, "href": "https://atcoder.jp/contests/abc279", "event": "TOYOTA SYSTEMS Programming Contest 2022(AtCoder Beginner Contest 279)", "duration": 60000, "start_time": 166946400000, "end_time": 166947000000}, {"id": 10002, "href": "https://www.codechef.com/START66", "event": "Starters 66", "duration": 108000, "start_time": 166921380000, "end_time": 166922460000}, {"id": 10001, "href": "http://codeforces.com/contests/1752", "event": "45th ICPC World Finals Challenge powered by Huawei - Problem 1", "duration": 12095400, "start_time": 166864320000, "end_time": 166985274000}, {"id": 10001, "href": "http://codeforces.com/contests/1751", "event": "45th ICPC World Finals Challenge powered by Huawei - Problem 2", "duration": 12095400, "start_time": 166864320000, "end_time": 166985274000}, {"id": 10002, "href": "https://www.codechef.com/START65", "event": "Starters 65", "duration": 108000, "start_time": 166860900000, "end_time": 166861980000}, {"id": 10001, "href": "http://codeforces.com/contests/1748", "event": "Codeforces Round (Div. 2)", "duration": 72000, "start_time": 166826370000, "end_time": 166827090000}, {"id": 10002, "href": "https://www.codechef.com/NOV221", "event": "November Long 2022 (Rated for Div 3 & 4)", "duration": 1548000, "start_time": 166826340000, "end_time": 166841820000}, {"id": 10004, "href": "https://atcoder.jp/contests/abc277", "event": "Daiwa Securities Co. Ltd. Programming Contest 2022 Autumn (AtCoder Beginner Contest 277)", "duration": 60000, "start_time": 166825440000, "end_time": 166826040000}, {"id": 10004, "href": "https://atcoder.jp/contests/ahc016", "event": "HACK TO THE FUTURE 2023 qual\uff08AtCoder Heuristic Contest 016\uff09", "duration": 7776000, "start_time": 166816080000, "end_time": 166893840000}, {"id": 10002, "href": "https://www.codechef.com/START64", "event": "Starters 64", "duration": 108000, "start_time": 166800420000, "end_time": 166801500000}, {"id": 10003, "href": "https://topcoder.com/community/events/", "event": "SRM 841", "duration": 72000, "start_time": 166790880000, "end_time": 166791600000}]}